odoo/addons/document_page_work_instruction/README.rst
odoo/addons/document_page_work_instruction/__init__.py
odoo/addons/document_page_work_instruction/__manifest__.py
odoo/addons/document_page_work_instruction/data/document_page.xml
odoo/addons/document_page_work_instruction/i18n/de.po
odoo/addons/document_page_work_instruction/i18n/document_page_work_instruction.pot
odoo/addons/document_page_work_instruction/i18n/document_page_work_instructions.pot
odoo/addons/document_page_work_instruction/i18n/es.po
odoo/addons/document_page_work_instruction/i18n/es_CO.po
odoo/addons/document_page_work_instruction/i18n/fr.po
odoo/addons/document_page_work_instruction/i18n/hr_HR.po
odoo/addons/document_page_work_instruction/i18n/it.po
odoo/addons/document_page_work_instruction/i18n/nb.po
odoo/addons/document_page_work_instruction/i18n/nl_NL.po
odoo/addons/document_page_work_instruction/i18n/nn.po
odoo/addons/document_page_work_instruction/i18n/no.po
odoo/addons/document_page_work_instruction/i18n/pt_BR.po
odoo/addons/document_page_work_instruction/i18n/sl.po
odoo/addons/document_page_work_instruction/i18n/vi.po
odoo/addons/document_page_work_instruction/static/description/icon.png
odoo/addons/document_page_work_instruction/views/document_page_work_instructions.xml
odoo11_addon_document_page_work_instruction-11.0.1.0.0.99.dev4.dist-info/METADATA
odoo11_addon_document_page_work_instruction-11.0.1.0.0.99.dev4.dist-info/RECORD
odoo11_addon_document_page_work_instruction-11.0.1.0.0.99.dev4.dist-info/WHEEL
odoo11_addon_document_page_work_instruction-11.0.1.0.0.99.dev4.dist-info/top_level.txt
